vectoralign/__init__.py
vectoralign/align.py
vectoralign-0.2.2.dist-info/licenses/LICENSE
vectoralign-0.2.2.dist-info/METADATA
vectoralign-0.2.2.dist-info/WHEEL
vectoralign-0.2.2.dist-info/top_level.txt
vectoralign-0.2.2.dist-info/RECORD
