Metadata-Version: 2.4
Name: vectoralign
Version: 0.2.2
Summary: Bilingual word alignment using multilingual embeddings - a spiritual implementation of SimAlign
Author: Mayank Joshi
License-Expression: MIT
Project-URL: Homepage, https://github.com/lothnic/vectoralign
Project-URL: Repository, https://github.com/lothnic/vectoralign
Project-URL: Issues, https://github.com/lothnic/vectoralign/issues
Keywords: nlp,alignment,bilingual,embeddings,translation,dictionary
Classifier: Development Status :: 3 - Alpha
Classifier: Intended Audience :: Developers
Classifier: Intended Audience :: Science/Research
Classifier: Programming Language :: Python :: 3
Classifier: Programming Language :: Python :: 3.10
Classifier: Programming Language :: Python :: 3.11
Classifier: Programming Language :: Python :: 3.12
Classifier: Topic :: Scientific/Engineering :: Artificial Intelligence
Classifier: Topic :: Text Processing :: Linguistic
Requires-Python: >=3.10
License-File: LICENSE
Requires-Dist: torch>=2.0.0
Requires-Dist: transformers>=4.30.0
Requires-Dist: numpy>=1.24.0
Requires-Dist: tqdm>=4.65.0
Requires-Dist: twine>=6.2.0
Provides-Extra: dev
Requires-Dist: build; extra == "dev"
Requires-Dist: twine; extra == "dev"
Requires-Dist: pytest; extra == "dev"
Dynamic: license-file
